Products.isurlinportal-3.0.1-py3.13-nspkg.pth
Products/isurlinportal/__init__.py
Products/isurlinportal/tests.py
products_isurlinportal-3.0.1.dist-info/METADATA
products_isurlinportal-3.0.1.dist-info/WHEEL
products_isurlinportal-3.0.1.dist-info/namespace_packages.txt
products_isurlinportal-3.0.1.dist-info/top_level.txt
products_isurlinportal-3.0.1.dist-info/RECORD
