Metadata-Version: 2.4
Name: Products.isurlinportal
Version: 3.0.1
Summary: Implementation of isURLInPortal method in Plone
Home-page: https://github.org/plone/Products.isurlinportal
Author: Plone Security Team
Author-email: security@plone.org
License: GPL
Keywords: plone security hotfix patch
Classifier: Development Status :: 5 - Production/Stable
Classifier: Framework :: Plone
Classifier: Framework :: Plone :: 6.1
Classifier: Framework :: Plone :: 6.2
Classifier: License :: OSI Approved :: GNU General Public License (GPL)
Classifier: Programming Language :: Python
Classifier: Programming Language :: Python :: 3.10
Classifier: Programming Language :: Python :: 3.11
Classifier: Programming Language :: Python :: 3.12
Classifier: Programming Language :: Python :: 3.13
Requires-Python: >=3.10
Requires-Dist: setuptools
Requires-Dist: plone.base
Requires-Dist: Zope>=5.10
Provides-Extra: test
Requires-Dist: Products.CMFPlone; extra == "test"
Dynamic: author
Dynamic: author-email
Dynamic: classifier
Dynamic: description
Dynamic: home-page
Dynamic: keywords
Dynamic: license
Dynamic: provides-extra
Dynamic: requires-dist
Dynamic: requires-python
Dynamic: summary
